sensirion_i2c_sen65/__init__.py
sensirion_i2c_sen65/commands.py
sensirion_i2c_sen65/device.py
sensirion_i2c_sen65/response_provider.py
sensirion_i2c_sen65/result_types.py
sensirion_i2c_sen65/version.py
sensirion_i2c_sen65-0.1.0.dist-info/LICENSE
sensirion_i2c_sen65-0.1.0.dist-info/METADATA
sensirion_i2c_sen65-0.1.0.dist-info/WHEEL
sensirion_i2c_sen65-0.1.0.dist-info/top_level.txt
sensirion_i2c_sen65-0.1.0.dist-info/RECORD
