Metadata-Version: 2.1
Name: sensirion-i2c-sen65
Version: 0.1.0
Summary: I2C driver for the Sensirion SEN65 sensor family
Author: Sensirion
Author-email: info@sensirion.com
License: BSD
Project-URL: Documentation, https://sensirion.github.io/python-i2c-sen65
Project-URL: Repository, https://github.com/Sensirion/python-i2c-sen65
Project-URL: Changelog, https://github.com/Sensirion/python-i2c-sen65/blob/master/CHANGELOG.md
Keywords: Sensirion SEN65
Classifier: Intended Audience :: Developers
Classifier: License :: OSI Approved :: BSD License
Classifier: Programming Language :: Python :: 3.6
Classifier: Programming Language :: Python :: 3.8
Classifier: Programming Language :: Python :: 3.11
Classifier: Topic :: Software Development :: Libraries :: Python Modules
Requires-Python: >=3.6, <4
License-File: LICENSE
Requires-Dist: sensirion-i2c-driver<2.0,>=1.0.0
Requires-Dist: sensirion-driver-adapters<3.0,>=2.1.9
Requires-Dist: sensirion-driver-support-types~=0.2.0
Requires-Dist: sensirion-shdlc-sensorbridge<0.3.0,>=0.1.0
Provides-Extra: test
Requires-Dist: flake8~=3.7.8; extra == "test"
Requires-Dist: pytest~=6.2.5; extra == "test"
Requires-Dist: pytest-cov~=3.0.0; extra == "test"
